docketanalyzer/__init__.py
docketanalyzer/config.py
docketanalyzer/agents/__init__.py
docketanalyzer/agents/agent.py
docketanalyzer/agents/tool.py
docketanalyzer/cli/__init__.py
docketanalyzer/cli/build.py
docketanalyzer/cli/configure.py
docketanalyzer/cli/connect.py
docketanalyzer/cli/format.py
docketanalyzer/cli/open.py
docketanalyzer/cli/sync.py
docketanalyzer/cli/test.py
docketanalyzer/docket/__init__.py
docketanalyzer/docket/docket_batch.py
docketanalyzer/docket/docket_index.py
docketanalyzer/docket/docket_manager.py
docketanalyzer/docket/choices/__init__.py
docketanalyzer/docket/choices/choice.py
docketanalyzer/docket/choices/court.py
docketanalyzer/docket/choices/docket.py
docketanalyzer/docket/choices/idb.py
docketanalyzer/docket/choices/judge.py
docketanalyzer/docket/choices/nature_suit.py
docketanalyzer/docket/choices/party.py
docketanalyzer/ml/.gitignore
docketanalyzer/ml/__init__.py
docketanalyzer/ml/pipelines/__init__.py
docketanalyzer/ml/pipelines/classification_pipeline.py
docketanalyzer/ml/pipelines/embedding_pipeline.py
docketanalyzer/ml/pipelines/multi_label_classification_pipeline.py
docketanalyzer/ml/pipelines/multi_task_pipeline.py
docketanalyzer/ml/pipelines/pipeline.py
docketanalyzer/ml/pipelines/remote_pipeline.py
docketanalyzer/ml/pipelines/token_classification_pipeline.py
docketanalyzer/ml/routines/__init__.py
docketanalyzer/ml/routines/classification_routine.py
docketanalyzer/ml/routines/multi_label_classification_routine.py
docketanalyzer/ml/routines/multi_task_routine.py
docketanalyzer/ml/routines/routine.py
docketanalyzer/ml/routines/token_classification_routine.py
docketanalyzer/ocr/__init__.py
docketanalyzer/ocr/document.py
docketanalyzer/ocr/layout.py
docketanalyzer/ocr/ocr.py
docketanalyzer/ocr/remote.py
docketanalyzer/ocr/utils.py
docketanalyzer/pacer/__init__.py
docketanalyzer/pacer/pacer.py
docketanalyzer/pacer/recap.py
docketanalyzer/services/__init__.py
docketanalyzer/services/elastic.py
docketanalyzer/services/psql.py
docketanalyzer-0.7.4.dist-info/METADATA
docketanalyzer-0.7.4.dist-info/WHEEL
docketanalyzer-0.7.4.dist-info/entry_points.txt
docketanalyzer-0.7.4.dist-info/licenses/LICENSE
docketanalyzer-0.7.4.dist-info/RECORD
